bnirs_algorithms/SRS.py
bnirs_algorithms/UCLn.py
bnirs_algorithms/__init__.py
bnirs_algorithms/values.csv
bnirs_algorithms-0.3.6.dist-info/LICENSE
bnirs_algorithms-0.3.6.dist-info/METADATA
bnirs_algorithms-0.3.6.dist-info/WHEEL
bnirs_algorithms-0.3.6.dist-info/top_level.txt
bnirs_algorithms-0.3.6.dist-info/RECORD
